cli/__init__.py
cli/config.py
cli/credentials.py
cli/database.py
cli/errors.py
cli/history.py
cli/llm.py
cli/logging.py
cli/main.py
cli/migrations.py
cli/models.py
cli/repl.py
cli/schema_introspection.py
cli/commands/__init__.py
cli/commands/config.py
cli/commands/connect.py
cli/commands/migrate.py
cli/commands/query.py
cli/commands/schema.py
cli/export/__init__.py
cli/export/exceptions.py
cli/export/exporter.py
cli/export/file_utils.py
cli/export/streaming.py
cli/formatting/__init__.py
cli/formatting/csv_formatter.py
cli/formatting/json_formatter.py
cli/formatting/markdown_formatter.py
cli/formatting/mermaid_formatter.py
cli/formatting/sql_formatter.py
cli/formatting/table.py
cli/schema_design/__init__.py
cli/schema_design/conversation.py
cli/schema_design/data_synthesizer.py
cli/schema_design/ddl_generator.py
cli/schema_design/file_analyzer.py
cli/schema_design/insertion_executor.py
cli/schema_design/schema_generator.py
cli/schema_design/session.py
cli/schema_design/test_data_generator.py
cli/schema_design/validator.py
cli/schema_design/visualizer.py
querynl_cli-0.2.7.dist-info/LICENSE
querynl_cli-0.2.7.dist-info/METADATA
querynl_cli-0.2.7.dist-info/WHEEL
querynl_cli-0.2.7.dist-info/entry_points.txt
querynl_cli-0.2.7.dist-info/top_level.txt
querynl_cli-0.2.7.dist-info/RECORD
