Metadata-Version: 2.1
Name: querynl-cli
Version: 0.2.7
Summary: AI-powered CLI for natural language database queries and automated test data generation
Home-page: https://github.com/dushshantha/QueryNL
Author: QueryNL Team
Author-email: QueryNL Team <contact@querynl.io>
License: MIT
Project-URL: Homepage, https://github.com/dushshantha/QueryNL
Project-URL: Documentation, https://github.com/dushshantha/QueryNL/blob/main/README.md
Project-URL: Repository, https://github.com/dushshantha/QueryNL
Project-URL: Issues, https://github.com/dushshantha/QueryNL/issues
Keywords: database,sql,natural-language,cli,test-data,faker,llm,ai
Classifier: Development Status :: 4 - Beta
Classifier: Intended Audience :: Developers
Classifier: Intended Audience :: System Administrators
Classifier: Topic :: Database
Classifier: Topic :: Software Development :: Code Generators
Classifier: Topic :: Utilities
Classifier: License :: OSI Approved :: MIT License
Classifier: Programming Language :: Python :: 3
Classifier: Programming Language :: Python :: 3.10
Classifier: Programming Language :: Python :: 3.11
Classifier: Programming Language :: Python :: 3.12
Classifier: Operating System :: OS Independent
Requires-Python: >=3.10
License-File: LICENSE
Requires-Dist: click (>=8.1.0)
Requires-Dist: click-repl (>=0.3.0)
Requires-Dist: rich (>=13.0.0)
Requires-Dist: prompt-toolkit (>=3.0.52)
Requires-Dist: keyring (>=25.0.0)
Requires-Dist: keyrings.cryptfile (>=1.3.0)
Requires-Dist: psycopg2-binary (>=2.9.0)
Requires-Dist: pymysql (>=1.0.0)
Requires-Dist: pymongo (>=4.0.0)
Requires-Dist: pyyaml (>=6.0.0)
Requires-Dist: pydantic (>=2.0.0)
Requires-Dist: httpx (>=0.27.0)
Requires-Dist: openai (>=1.0.0)
Requires-Dist: anthropic (>=0.7.0)
Requires-Dist: langchain (>=0.1.0)
Requires-Dist: langchain-core (>=0.1.0)
Requires-Dist: langchain-openai (>=0.0.2)
Requires-Dist: langchain-anthropic (>=0.0.1)
Requires-Dist: pandas (>=2.0.0)
Requires-Dist: openpyxl (>=3.0.0)
Requires-Dist: sqlalchemy (>=2.0.0)
Requires-Dist: Faker (>=24.0.0)
Requires-Dist: toposort (>=1.10)
Requires-Dist: pytest (>=8.0.0)
Requires-Dist: pytest-cov (>=4.0.0)
Requires-Dist: pytest-mock (>=3.12.0)
Requires-Dist: ruff (>=0.1.0)
